ImageCreator/GUI.py
ImageCreator/__init__.py
ImageCreator/core/__init__.py
ImageCreator/core/image_create.py
ImageCreator/core/make_template.py
ImageCreator/core/use.py
ImageCreator/core/utils.py
ImageCreator-0.0.2.dist-info/LICENSE
ImageCreator-0.0.2.dist-info/METADATA
ImageCreator-0.0.2.dist-info/WHEEL
ImageCreator-0.0.2.dist-info/top_level.txt
ImageCreator-0.0.2.dist-info/RECORD
