Metadata-Version: 2.1
Name: ImageCreator
Version: 0.0.2
Summary: A software to create images from a yaml template
Home-page: https://github.com/enocyzed/ImageCreator
Author: Enoch
Author-email: enocyzed@gmail.com
License: Apache License 2.0
Platform: UNKNOWN
Classifier: Programming Language :: Python :: 3
Classifier: Programming Language :: Python :: 3.9
Classifier: License :: OSI Approved :: Apache Software License
Classifier: Operating System :: OS Independent
Requires-Dist: pyyaml (>=5.1)
Provides-Extra: dev
Requires-Dist: pytest (>=3.7) ; extra == 'dev'
